arrr.py
arrr-1.0.6.dist-info/licenses/AUTHORS
arrr-1.0.6.dist-info/licenses/LICENSE
arrr-1.0.6.dist-info/METADATA
arrr-1.0.6.dist-info/WHEEL
arrr-1.0.6.dist-info/entry_points.txt
arrr-1.0.6.dist-info/top_level.txt
arrr-1.0.6.dist-info/RECORD
