Metadata-Version: 2.4
Name: arrr
Version: 1.0.6
Summary: A module and command to turn English into Pirate speak.
Home-page: https://github.com/ntoll/arrr
Author: Nicholas H.Tollervey
Author-email: ntoll@ntoll.org
License: MIT
Classifier: Development Status :: 5 - Production/Stable
Classifier: Environment :: Console
Classifier: Intended Audience :: Developers
Classifier: Intended Audience :: Education
Classifier: License :: OSI Approved :: MIT License
Classifier: Natural Language :: English
Classifier: Programming Language :: Python :: 3.5
Classifier: Topic :: Education
Classifier: Topic :: Communications
Classifier: Topic :: Software Development :: Internationalization
License-File: LICENSE
License-File: AUTHORS
Dynamic: author
Dynamic: author-email
Dynamic: classifier
Dynamic: description
Dynamic: home-page
Dynamic: license
Dynamic: license-file
Dynamic: summary
